fileformats/datascience/__init__.py
fileformats/datascience/_version.py
fileformats/datascience/data.py
fileformats/datascience/image.py
fileformats/datascience/object_serialization.py
fileformats/datascience/py.typed
fileformats/datascience/scripts.py
fileformats_datascience-0.4.0.dist-info/METADATA
fileformats_datascience-0.4.0.dist-info/WHEEL
fileformats_datascience-0.4.0.dist-info/licenses/LICENSE
fileformats_datascience-0.4.0.dist-info/RECORD
