Metadata-Version: 2.4
Name: fileformats-datascience
Version: 0.4.0
Summary: Classes for representing datascience file formats in Python classes for use in type hinting in data workflows
Project-URL: repository, https://github.com/ArcanaFramework/fileformats-datascience
Author-email: "Thomas G. Close" <tom.g.close@gmail.com>
Maintainer-email: "Thomas G. Close" <tom.g.close@gmail.com>
License: Creative Commons Attribution 4.0 International Public License
License-File: LICENSE
Keywords: data,file formats
Classifier: Development Status :: 3 - Alpha
Classifier: Environment :: Console
Classifier: Intended Audience :: Science/Research
Classifier: License :: OSI Approved :: Apache Software License
Classifier: Operating System :: MacOS :: MacOS X
Classifier: Operating System :: Microsoft :: Windows
Classifier: Operating System :: POSIX :: Linux
Classifier: Programming Language :: Python :: 3.8
Classifier: Programming Language :: Python :: 3.9
Classifier: Programming Language :: Python :: 3.10
Classifier: Programming Language :: Python :: 3.11
Classifier: Topic :: Scientific/Engineering
Requires-Python: >=3.8
Requires-Dist: fileformats>=0.8
Provides-Extra: dev
Requires-Dist: black; extra == 'dev'
Requires-Dist: codecov; extra == 'dev'
Requires-Dist: codespell; extra == 'dev'
Requires-Dist: flake8; extra == 'dev'
Requires-Dist: flake8-pyproject; extra == 'dev'
Requires-Dist: h5py; extra == 'dev'
Requires-Dist: mypy>=1.5.1; extra == 'dev'
Requires-Dist: pre-commit; extra == 'dev'
Requires-Dist: pytest-cov>=2.12.1; extra == 'dev'
Requires-Dist: pytest-env>=0.6.2; extra == 'dev'
Requires-Dist: pytest>=6.2.5; extra == 'dev'
Requires-Dist: rpy2; extra == 'dev'
Requires-Dist: scipy; extra == 'dev'
Provides-Extra: test
Requires-Dist: codecov; extra == 'test'
Requires-Dist: h5py; extra == 'test'
Requires-Dist: pytest-cov>=2.12.1; extra == 'test'
Requires-Dist: pytest-env>=0.6.2; extra == 'test'
Requires-Dist: pytest>=6.2.5; extra == 'test'
Requires-Dist: rpy2; extra == 'test'
Requires-Dist: scipy; extra == 'test'
